fattmerchant/__init__.py
fattmerchant/client.py
fattmerchant/exceptions.py
fattmerchant/request.py
fattmerchant/utils.py
fattmerchant/controllers/__init__.py
fattmerchant/controllers/charges.py
fattmerchant/controllers/customers.py
fattmerchant/controllers/deposits.py
fattmerchant/controllers/paymentmethods.py
fattmerchant/controllers/teams.py
fattmerchant/controllers/transactions.py
fattmerchant/models/__init__.py
fattmerchant/models/customer.py
fattmerchant/models/deposit.py
fattmerchant/models/merchant.py
fattmerchant/models/payment_method.py
fattmerchant/models/team.py
fattmerchant/models/team_registration.py
fattmerchant/models/transaction.py
fattmerchant/models/user.py
fattmerchant-2.0.1.dist-info/LICENSE
fattmerchant-2.0.1.dist-info/METADATA
fattmerchant-2.0.1.dist-info/WHEEL
fattmerchant-2.0.1.dist-info/top_level.txt
fattmerchant-2.0.1.dist-info/RECORD
