Metadata-Version: 2.1
Name: fattmerchant
Version: 2.0.1
Summary: Python 3.x Client for Fattmerchant's Omni API
Home-page: https://github.com/fattmerchantorg/fattmerchant_python_client
Author: Fattmerchant INC
Author-email: support@fattmerchant.com
License: UNKNOWN
Platform: UNKNOWN
Classifier: Programming Language :: Python :: 3
Classifier: License :: OSI Approved :: MIT License
Classifier: Operating System :: OS Independent
Requires-Python: >=3.5
Requires-Dist: ddt
Requires-Dist: requests
